{
  "name": "02",
  "timestamp": "2025-10-08T11:14:32.524Z",
  "animation": {
    "loop": true,
    "speedFactor": 1.65
  },
  "camera": {
    "fov": 75,
    "mode": "perspective"
  },
  "coordinates": {
    "dataSpace": {
      "scale": 1.4
    }
  },
  "environment": {
    "pathColor": "#F0B7B7"
  },
  "particles": {
    "breathIntensity": 0.26,
    "dustColor": "#AF85B7",
    "dustCount": 2600,
    "dustOpacity": 0.83,
    "dustSize": 0.78,
    "floatIntensity": 0.64,
    "rotationSpeed": 0,
    "rotationTiltXY": -20,
    "rotationTiltXZ": 43,
    "systemScale": 1
  },
  "path": {
    "depthIntensity": 0.5,
    "scale": 1.6
  },
  "postprocess": {
    "enabled": true,
    "bloom": {
      "enabled": true,
      "intensity": 0.9,
      "luminanceSmoothing": 0.2,
      "luminanceThreshold": 0.1
    },
    "brightnessContrast": {
      "brightness": 0,
      "contrast": 0,
      "enabled": true
    },
    "film": {
      "enabled": true,
      "noiseIntensity": 0.29,
      "scanlineCount": 3136,
      "scanlineIntensity": 0.48
    },
    "hueSaturation": {
      "enabled": true,
      "hue": 0.65,
      "saturation": 0.04
    }
  }
}
